{
  "chapter": "1 Corinthians 5",
  "sermons": [
    {
      "sermon_id": "09KQDExB3yQ",
      "sermon_title": "Sermon 09KQDExB3yQ",
      "url": "https://www.youtube.com/watch?v=09KQDExB3yQ",
      "publish_date": "2025-04-28",
      "occurrences": [
        {
          "reference": "1 Corinthians 5",
          "sermon_id": "09KQDExB3yQ",
          "timestamp": 375.8800048828125,
          "context": "...entions about his place in the birth order, that he's his firstborn. We notice and we could look in 1 Corinthians 5, you might wanna reference it, verses one and two, how that his birthright was forfeited and theref..."
        }
      ]
    }
  ]
}