{
  "chapter": "Acts 5",
  "sermons": [
    {
      "sermon_id": "QRS13lJ0CSY",
      "sermon_title": "Sermon QRS13lJ0CSY",
      "url": "https://www.youtube.com/watch?v=QRS13lJ0CSY",
      "publish_date": "2025-04-26",
      "occurrences": [
        {
          "reference": "Acts 5",
          "sermon_id": "QRS13lJ0CSY",
          "timestamp": 1082.0400085449219,
          "context": ".... Many of us would be familiar with the account here of Ananias and Sapphira. The Bible tells us in Acts 5 in verse number 1, but a certain man named Ananias with Sapphira, his wife, sold a possession. And ..."
        },
        {
          "reference": "Acts 5",
          "sermon_id": "QRS13lJ0CSY",
          "timestamp": 1143.7999877929688,
          "context": "with the account here of Ananias and Sapphira. The Bible tells us in Acts 5 in verse number 1, but a certain man named Ananias with Sapphira, his wife, sold a possession. And ..."
        }
      ]
    },
    {
      "sermon_id": "EoTOjgo0SqY",
      "sermon_title": "Sermon EoTOjgo0SqY",
      "url": "https://www.youtube.com/watch?v=EoTOjgo0SqY",
      "publish_date": "2025-04-26",
      "occurrences": [
        {
          "reference": "Acts 5",
          "sermon_id": "EoTOjgo0SqY",
          "timestamp": 2221.4200134277344,
          "context": ".... But I want to remind you of Acts chapter number 4. And in this passage of Scripture, we looked at Acts 5 this morning. But in Acts chapter number 4, again, the religious leaders are not happy with all tha..."
        }
      ]
    },
    {
      "sermon_id": "TOJWIvB7SDM",
      "sermon_title": "Sermon TOJWIvB7SDM",
      "url": "https://www.youtube.com/watch?v=TOJWIvB7SDM",
      "publish_date": "2025-04-26",
      "occurrences": [
        {
          "reference": "Acts 5",
          "sermon_id": "TOJWIvB7SDM",
          "timestamp": 1855.6600494384766,
          "context": "...th. Think of this in Proverbs chapter 6. We won't take time to turn there because I want to look at Acts 5. But in Proverbs chapter 6 and verses 16 through 19, God gives us things that are an abomination, t..."
        },
        {
          "reference": "Acts 5",
          "sermon_id": "TOJWIvB7SDM",
          "timestamp": 1980.7000579833984,
          "context": "...oday. But I wonder if he did, what kind of an effect it would have upon us as the people of God. In Acts 5, the Bible tells us of a particular account. It says this in verse number 1, but a certain man name..."
        }
      ]
    },
    {
      "sermon_id": "d8tHudo0_3I",
      "sermon_title": "Sermon d8tHudo0_3I",
      "url": "https://www.youtube.com/watch?v=d8tHudo0_3I",
      "publish_date": "2025-04-26",
      "occurrences": [
        {
          "reference": "Acts 5",
          "sermon_id": "d8tHudo0_3I",
          "timestamp": 79.12000274658203,
          "context": "...t he's told us to do We see that he blesses beyond measure the first of those statements is made in Acts 5 in verse 28 when those that are"
        },
        {
          "reference": "Acts 5",
          "sermon_id": "d8tHudo0_3I",
          "timestamp": 145.83999633789062,
          "context": "...t he's told us to do We see that he blesses beyond measure the first of those statements is made in Acts 5 in verse 28 when those that are Opposing the work of the ministry say this ye have filled Jerusalem..."
        }
      ]
    }
  ]
}