{
  "chapter": "Genesis 17",
  "sermons": [
    {
      "sermon_id": "bsk8iNEnRVo",
      "sermon_title": "Sermon bsk8iNEnRVo",
      "url": "https://www.youtube.com/watch?v=bsk8iNEnRVo",
      "publish_date": "2025-04-26",
      "occurrences": [
        {
          "reference": "Genesis 17",
          "sermon_id": "bsk8iNEnRVo",
          "timestamp": 1838.479995727539,
          "context": "... Abraham about El Elyon, the Most High God, the Possessor of heaven and earth. We find that it's in Genesis 17 that God reveals Himself to Abraham as El Shaddai. Notice the Bible says in verse number one, \"'And..."
        },
        {
          "reference": "Genesis 17",
          "sermon_id": "bsk8iNEnRVo",
          "timestamp": 1838.479995727539,
          "context": "... Abraham about El Elyon, the Most High God, the Possessor of heaven and earth. We find that it's in Genesis 17 that God reveals Himself to Abraham as El Shaddai. Notice the Bible says in verse number one, \"'And..."
        },
        {
          "reference": "Genesis 17",
          "sermon_id": "bsk8iNEnRVo",
          "timestamp": 1994.0,
          "context": "... verse number seven, it's oft repeated throughout this passage of Scripture. The Bible says this in Genesis 17 in verse number seven, \"'And I will establish My covenant between Me and thee and thy seed after th..."
        },
        {
          "reference": "Genesis 17",
          "sermon_id": "bsk8iNEnRVo",
          "timestamp": 2067.720001220703,
          "context": "Bible says this in Genesis 17 in verse number seven, \"'And I will establish My covenant between Me and thee and thy seed after th..."
        }
      ]
    }
  ]
}