{
  "chapter": "Jeremiah 6",
  "sermons": [
    {
      "sermon_id": "t3763lfMrgQ",
      "sermon_title": "Sermon t3763lfMrgQ",
      "url": "https://www.youtube.com/watch?v=t3763lfMrgQ",
      "publish_date": "2025-04-28",
      "occurrences": [
        {
          "reference": "Jeremiah 6",
          "sermon_id": "t3763lfMrgQ",
          "timestamp": 1296.6400146484375,
          "context": "...mazing? And that's what the marketing industry, that's what they do, that's why they exist. Look at Jeremiah 6 and verse 13. For from the least of them, even unto the greatest of them, every one is given to cov..."
        }
      ]
    }
  ]
}