{
  "chapter": "Luke 2",
  "sermons": [
    {
      "sermon_id": "d8tHudo0_3I",
      "sermon_title": "Sermon d8tHudo0_3I",
      "url": "https://www.youtube.com/watch?v=d8tHudo0_3I",
      "publish_date": "2025-04-26",
      "occurrences": [
        {
          "reference": "Luke 2",
          "sermon_id": "d8tHudo0_3I",
          "timestamp": 415.79998779296875,
          "context": "...ys I bring unto you what shall be to all people this wonderful Proclamation that was given there in Luke 2 was not to just be given to the shepherds and held by the shepherds But they were to go and proclai..."
        }
      ]
    }
  ]
}