{
  "chapter": "Matthew 7",
  "sermons": [
    {
      "sermon_id": "WhaPo-g3nqA",
      "sermon_title": "Sermon WhaPo-g3nqA",
      "url": "https://www.youtube.com/watch?v=WhaPo-g3nqA",
      "publish_date": "2025-04-26",
      "occurrences": [
        {
          "reference": "Matthew 7",
          "sermon_id": "WhaPo-g3nqA",
          "timestamp": 2377.3799438476562,
          "context": "...uth that God has given to us. Really, Jesus said it this way, and we're familiar with this truth in Matthew 7 and verse number 20, when He said, wherefore, by their fruits ye shall know them. Ye shall know the..."
        }
      ]
    },
    {
      "sermon_id": "BTHY_qWho6M",
      "sermon_title": "Sermon BTHY_qWho6M",
      "url": "https://www.youtube.com/watch?v=BTHY_qWho6M",
      "publish_date": "2025-04-26",
      "occurrences": [
        {
          "reference": "Matthew 7",
          "sermon_id": "BTHY_qWho6M",
          "timestamp": 1839.4399642944336,
          "context": "...ing what she received. Look at Matthew. Actually, turn to Mark. I want to look at what Mark says in Matthew 7, verses 29 and 30. Notice the Bible says this in Mark 7, verse 29,"
        },
        {
          "reference": "Matthew 7",
          "sermon_id": "BTHY_qWho6M",
          "timestamp": 1924.199966430664,
          "context": "...ing what she received. Look at Matthew. Actually, turn to Mark. I want to look at what Mark says in Matthew 7, verses 29 and 30. Notice the Bible says this in Mark 7, verse 29, \"...and He said unto her, for th..."
        }
      ]
    }
  ]
}