{
  "6": [
    {
      "before_verse": 1,
      "title": "Complaint of the Grecian Widows"
    },
    {
      "before_verse": 2,
      "title": "Seven Men Chosen"
    },
    {
      "before_verse": 8,
      "title": "Stephen Opposed and Arrested"
    }
  ],
  "3": [
    {
      "before_verse": 1,
      "title": "A Lame Man Healed at the Temple"
    },
    {
      "before_verse": 11,
      "title": "Peter Addresses the Crowd in Solomon's Porch"
    }
  ],
  "4": [
    {
      "before_verse": 1,
      "title": "Peter and John Arrested"
    },
    {
      "before_verse": 5,
      "title": "Peter Speaks Before the Council"
    },
    {
      "before_verse": 15,
      "title": "The Council Deliberates"
    },
    {
      "before_verse": 23,
      "title": "The Believers Pray Together"
    },
    {
      "before_verse": 32,
      "title": "The Church Shares All Things"
    }
  ],
  "2": [
    {
      "before_verse": 1,
      "title": "The Coming of the Holy Spirit"
    },
    {
      "before_verse": 5,
      "title": "The Crowd's Reaction"
    },
    {
      "before_verse": 14,
      "title": "Peter's Address to the Crowd"
    },
    {
      "before_verse": 37,
      "title": "The Response and Baptism"
    },
    {
      "before_verse": 42,
      "title": "The Believers' Common Life"
    }
  ],
  "8": [
    {
      "before_verse": 1,
      "title": "Persecution Scatters the Church"
    },
    {
      "before_verse": 5,
      "title": "Philip Preaches in Samaria"
    },
    {
      "before_verse": 14,
      "title": "Peter and John Sent to Samaria"
    },
    {
      "before_verse": 26,
      "title": "Philip and the Ethiopian Eunuch"
    }
  ],
  "7": [
    {
      "before_verse": 1,
      "title": "Stephen's Defense Before the Council"
    },
    {
      "before_verse": 2,
      "title": "Israel's History from Abraham to Moses"
    },
    {
      "before_verse": 44,
      "title": "The Tabernacle and Temple"
    },
    {
      "before_verse": 51,
      "title": "Stephen Rebukes the Council"
    },
    {
      "before_verse": 54,
      "title": "Stephen Stoned"
    }
  ],
  "5": [
    {
      "before_verse": 1,
      "title": "Ananias and Sapphira Struck Dead"
    },
    {
      "before_verse": 12,
      "title": "Signs and Wonders Among the People"
    },
    {
      "before_verse": 17,
      "title": "The Apostles Arrested and Freed"
    },
    {
      "before_verse": 27,
      "title": "The Apostles Before the Council"
    },
    {
      "before_verse": 34,
      "title": "Gamaliel's Counsel"
    }
  ],
  "9": [
    {
      "before_verse": 1,
      "title": "Saul Persecutes the Church"
    },
    {
      "before_verse": 3,
      "title": "Saul's Conversion near Damascus"
    },
    {
      "before_verse": 10,
      "title": "Ananias Sent to Saul"
    },
    {
      "before_verse": 20,
      "title": "Saul Preaches at Damascus and Jerusalem"
    },
    {
      "before_verse": 32,
      "title": "Peter Heals Aeneas and Raises Dorcas"
    }
  ],
  "1": [
    {
      "before_verse": 1,
      "title": "Prologue to Theophilus"
    },
    {
      "before_verse": 4,
      "title": "Jesus Commands the Disciples to Wait"
    },
    {
      "before_verse": 9,
      "title": "The Ascension"
    },
    {
      "before_verse": 15,
      "title": "Matthias Chosen to Replace Judas"
    }
  ],
  "11": [
    {
      "before_verse": 1,
      "title": "Peter Questioned at Jerusalem"
    },
    {
      "before_verse": 4,
      "title": "Peter Recounts His Vision"
    },
    {
      "before_verse": 19,
      "title": "The Gospel Reaches Antioch"
    },
    {
      "before_verse": 27,
      "title": "Agabus Foretells a Famine"
    }
  ],
  "10": [
    {
      "before_verse": 1,
      "title": "Cornelius Receives a Vision"
    },
    {
      "before_verse": 9,
      "title": "Peter's Vision at Joppa"
    },
    {
      "before_verse": 17,
      "title": "The Messengers Arrive"
    },
    {
      "before_verse": 24,
      "title": "Peter Meets Cornelius"
    },
    {
      "before_verse": 44,
      "title": "The Holy Ghost Falls on the Gentiles"
    }
  ],
  "12": [
    {
      "before_verse": 1,
      "title": "Herod Persecutes the Church"
    },
    {
      "before_verse": 6,
      "title": "Peter Freed from Prison"
    },
    {
      "before_verse": 12,
      "title": "Peter Returns to the Believers"
    },
    {
      "before_verse": 20,
      "title": "The Death of Herod"
    }
  ],
  "13": [
    {
      "before_verse": 1,
      "title": "Barnabas and Saul Sent from Antioch"
    },
    {
      "before_verse": 6,
      "title": "Elymas the Sorcerer Struck Blind"
    },
    {
      "before_verse": 14,
      "title": "Paul Preaches in Antioch of Pisidia"
    },
    {
      "before_verse": 44,
      "title": "The Gospel Turned to the Gentiles"
    }
  ],
  "15": [
    {
      "before_verse": 1,
      "title": "The Circumcision Dispute Arises"
    },
    {
      "before_verse": 6,
      "title": "The Council at Jerusalem"
    },
    {
      "before_verse": 22,
      "title": "The Letter to the Gentile Churches"
    },
    {
      "before_verse": 36,
      "title": "Paul and Barnabas Part Ways"
    }
  ],
  "14": [
    {
      "before_verse": 1,
      "title": "Paul and Barnabas at Iconium"
    },
    {
      "before_verse": 8,
      "title": "A Cripple Healed at Lystra"
    },
    {
      "before_verse": 11,
      "title": "The Crowd Calls Them Gods"
    },
    {
      "before_verse": 19,
      "title": "Paul Stoned and Left for Dead"
    },
    {
      "before_verse": 21,
      "title": "Return to Antioch"
    }
  ],
  "16": [
    {
      "before_verse": 1,
      "title": "Timothy Joins Paul"
    },
    {
      "before_verse": 6,
      "title": "The Macedonian Call"
    },
    {
      "before_verse": 13,
      "title": "Lydia's Conversion at Philippi"
    },
    {
      "before_verse": 16,
      "title": "Paul and Silas Imprisoned"
    },
    {
      "before_verse": 25,
      "title": "The Philippian Jailer Converted"
    }
  ],
  "18": [
    {
      "before_verse": 1,
      "title": "Paul at Corinth"
    },
    {
      "before_verse": 9,
      "title": "The Lord's Vision to Paul"
    },
    {
      "before_verse": 12,
      "title": "Paul Before Gallio"
    },
    {
      "before_verse": 18,
      "title": "Paul Returns to Antioch"
    },
    {
      "before_verse": 24,
      "title": "Apollos at Ephesus"
    }
  ],
  "21": [
    {
      "before_verse": 1,
      "title": "The Voyage to Jerusalem"
    },
    {
      "before_verse": 8,
      "title": "Paul at Caesarea; Agabus's Warning"
    },
    {
      "before_verse": 17,
      "title": "Paul Meets with James and the Elders"
    },
    {
      "before_verse": 27,
      "title": "Paul Seized in the Temple"
    }
  ],
  "23": [
    {
      "before_verse": 1,
      "title": "Paul Before the Council"
    },
    {
      "before_verse": 11,
      "title": "The Lord Appears to Paul"
    },
    {
      "before_verse": 12,
      "title": "The Plot Against Paul"
    },
    {
      "before_verse": 23,
      "title": "Paul Sent to Felix"
    }
  ],
  "19": [
    {
      "before_verse": 1,
      "title": "Disciples at Ephesus Rebaptized"
    },
    {
      "before_verse": 8,
      "title": "Paul Teaches at Ephesus"
    },
    {
      "before_verse": 11,
      "title": "Miracles and the Sons of Sceva"
    },
    {
      "before_verse": 21,
      "title": "Paul Plans to Leave for Jerusalem"
    },
    {
      "before_verse": 23,
      "title": "The Riot of the Silversmiths"
    }
  ],
  "22": [
    {
      "before_verse": 1,
      "title": "Paul Addresses the Crowd"
    },
    {
      "before_verse": 6,
      "title": "Paul Recounts His Conversion"
    },
    {
      "before_verse": 12,
      "title": "Ananias Restores Paul's Sight"
    },
    {
      "before_verse": 22,
      "title": "The Crowd Rejects Paul"
    },
    {
      "before_verse": 25,
      "title": "Paul Claims Roman Citizenship"
    }
  ],
  "20": [
    {
      "before_verse": 1,
      "title": "Paul Travels Through Macedonia and Greece"
    },
    {
      "before_verse": 7,
      "title": "Eutychus Raised at Troas"
    },
    {
      "before_verse": 13,
      "title": "Voyage to Miletus"
    },
    {
      "before_verse": 17,
      "title": "Paul's Farewell Address to the Ephesian Elders"
    }
  ],
  "17": [
    {
      "before_verse": 1,
      "title": "Paul Preaches at Thessalonica"
    },
    {
      "before_verse": 10,
      "title": "The Bereans Receive the Word"
    },
    {
      "before_verse": 16,
      "title": "Paul at Athens"
    },
    {
      "before_verse": 22,
      "title": "Paul's Address on Mars' Hill"
    },
    {
      "before_verse": 32,
      "title": "Mixed Response at Athens"
    }
  ],
  "25": [
    {
      "before_verse": 1,
      "title": "Festus Visits Jerusalem"
    },
    {
      "before_verse": 6,
      "title": "Paul Before Festus at Caesarea"
    },
    {
      "before_verse": 11,
      "title": "Paul Appeals to Caesar"
    },
    {
      "before_verse": 13,
      "title": "Agrippa and Bernice Visit Festus"
    },
    {
      "before_verse": 23,
      "title": "Paul Brought Before Agrippa"
    }
  ],
  "24": [
    {
      "before_verse": 1,
      "title": "Tertullus Accuses Paul Before Felix"
    },
    {
      "before_verse": 10,
      "title": "Paul's Defense Before Felix"
    },
    {
      "before_verse": 22,
      "title": "Felix Defers Judgment"
    },
    {
      "before_verse": 24,
      "title": "Felix Hears Paul Again"
    }
  ],
  "26": [
    {
      "before_verse": 1,
      "title": "Paul Addresses Agrippa"
    },
    {
      "before_verse": 4,
      "title": "Paul's Life as a Pharisee"
    },
    {
      "before_verse": 12,
      "title": "Paul's Vision on the Road to Damascus"
    },
    {
      "before_verse": 24,
      "title": "Festus and Agrippa Respond"
    },
    {
      "before_verse": 30,
      "title": "Agrippa Declares Paul Innocent"
    }
  ],
  "28": [
    {
      "before_verse": 1,
      "title": "Ashore at Malta"
    },
    {
      "before_verse": 7,
      "title": "Paul Heals the Sick"
    },
    {
      "before_verse": 11,
      "title": "Voyage to Rome"
    },
    {
      "before_verse": 17,
      "title": "Paul Addresses the Roman Jews"
    },
    {
      "before_verse": 30,
      "title": "Paul Preaches in Rome"
    }
  ],
  "27": [
    {
      "before_verse": 1,
      "title": "Paul Sails for Rome"
    },
    {
      "before_verse": 9,
      "title": "Paul Warns Against Sailing"
    },
    {
      "before_verse": 14,
      "title": "The Storm at Sea"
    },
    {
      "before_verse": 21,
      "title": "Paul Encourages the Crew"
    },
    {
      "before_verse": 39,
      "title": "The Shipwreck"
    }
  ]
}