{
  "reference": "Deuteronomy 25",
  "occurrences": [
    {
      "sermon_id": "hwLKY1FAuwU",
      "timestamp": 930.6200256347656,
      "text": "want to give God's Word. It's the responsibility. But let me say this, not only does the pastor have a responsibility, the church has a responsibility. He says in verse number 18, notice what he says, for the scripture saith. This is a biblical truth. This is not just Timothy, Paul's opinion that he's given to Timothy. He says, this is a, the scripture saith. This is a biblical truth. By the way, when he uses this phrase and says, for the scripture saith, he references really two verses of scripture. Thou shall not muzzle the ox that treadeth out the corn, and the laborer is worthy of his reward. We're not going to take the time, but if you went back to Deuteronomy 25 in verse number four, and if you went back to Luke chapter 10 in verse number seven, those are the two references that are given to us in verse number 18. And we find that Paul, under the inspiration of the Holy Spirit of God, refers to both of those as being scripture. And that's an important thing for us to understand. I'm so thankful for the scripture, for the word of God, for thus saith the Lord. And so what does he say? He says that the, in verse number 17, let the elders that rule well be counted worthy of double honor, especially they who labor in the word and",
      "context": "... and the laborer is worthy of his reward. We're not going to take the time, but if you went back to Deuteronomy 25 in verse number four, and if you went back to Luke chapter 10 in verse number seven, those are the ...",
      "sermon_title": "\"Honorable Elders\" I Timothy 5:17-25",
      "url": "https://www.youtube.com/watch?v=hwLKY1FAuwU&t=930",
      "channel": "Unknown",
      "publish_date": 20240623
    }
  ]
}