{
  "book": "1 Corinthians",
  "sermons": [
    {
      "sermon_id": "G38C0Tuh6UA",
      "sermon_title": "Sermon G38C0Tuh6UA",
      "url": "https://www.youtube.com/watch?v=G38C0Tuh6UA",
      "publish_date": "2025-04-26",
      "occurrences": [
        {
          "reference": "1 Corinthians 15",
          "sermon_id": "G38C0Tuh6UA",
          "timestamp": 2388.9799194335938,
          "context": "...ower over us. If we've been saved by the grace of God, we will, listen, Christ is the first fruits, 1 Corinthians 15, we will rise again. And what a joy that is. And he says that he'll present us. I want you to think..."
        }
      ]
    },
    {
      "sermon_id": "jNCO80tyoMQ",
      "sermon_title": "Sermon jNCO80tyoMQ",
      "url": "https://www.youtube.com/watch?v=jNCO80tyoMQ",
      "publish_date": "2025-04-26",
      "occurrences": [
        {
          "reference": "1 Corinthians 15",
          "sermon_id": "jNCO80tyoMQ",
          "timestamp": 2527.9400024414062,
          "context": "...e list of people that are against us. Yeah, I do too. But with God, we're a majority, amen? Look at 1 Corinthians 15."
        },
        {
          "reference": "1 Corinthians 15",
          "sermon_id": "jNCO80tyoMQ",
          "timestamp": 2601.539993286133,
          "context": "...e list of people that are against us. Yeah, I do too. But with God, we're a majority, amen? Look at 1 Corinthians 15. We mentioned that one of the ways in which Nehemiah resisted the enemy was that he remained steadf..."
        },
        {
          "reference": "1 Corinthians 15",
          "sermon_id": "jNCO80tyoMQ",
          "timestamp": 2601.539993286133,
          "context": "...e list of people that are against us. Yeah, I do too. But with God, we're a majority, amen? Look at 1 Corinthians 15. We mentioned that one of the ways in which Nehemiah resisted the enemy was that he remained steadf..."
        }
      ]
    },
    {
      "sermon_id": "EetmC5JSFHc",
      "sermon_title": "Sermon EetmC5JSFHc",
      "url": "https://www.youtube.com/watch?v=EetmC5JSFHc",
      "publish_date": "2025-04-26",
      "occurrences": [
        {
          "reference": "1 Corinthians 15",
          "sermon_id": "EetmC5JSFHc",
          "timestamp": 2056.540008544922,
          "context": "... as if, is it even working? Is there even any purpose? Is there any progress that's being made? But 1 Corinthians 15 and verse number 58 reminds us that God has promised to us that our labor, our work is not in vain ..."
        }
      ]
    },
    {
      "sermon_id": "BZi-sUEn51M",
      "sermon_title": "Sermon BZi-sUEn51M",
      "url": "https://www.youtube.com/watch?v=BZi-sUEn51M",
      "publish_date": "2025-04-26",
      "occurrences": [
        {
          "reference": "1 Corinthians 13",
          "sermon_id": "BZi-sUEn51M",
          "timestamp": 599.97998046875,
          "context": "...e, long-suffering, and we think about the truth of charity or love. You know what the Bible says in 1 Corinthians 13 about love or charity? It says this, charity suffereth long. You know what that word is? It's the s..."
        },
        {
          "reference": "1 Corinthians 13",
          "sermon_id": "BZi-sUEn51M",
          "timestamp": 599.97998046875,
          "context": "...e, long-suffering, and we think about the truth of charity or love. You know what the Bible says in 1 Corinthians 13 about love or charity? It says this, charity suffereth long. You know what that word is? It's the s..."
        },
        {
          "reference": "1 Corinthians 13",
          "sermon_id": "BZi-sUEn51M",
          "timestamp": 667.1399841308594,
          "context": "...nt charity among yourselves. Fervent charity, this love, but the Bible describes charity or love in 1 Corinthians 13 as it suffereth long. And so this evening as we begin to understand and try to unwrap if you will t..."
        }
      ]
    },
    {
      "sermon_id": "QRS13lJ0CSY",
      "sermon_title": "Sermon QRS13lJ0CSY",
      "url": "https://www.youtube.com/watch?v=QRS13lJ0CSY",
      "publish_date": "2025-04-26",
      "occurrences": [
        {
          "reference": "1 Corinthians 11",
          "sermon_id": "QRS13lJ0CSY",
          "timestamp": 1271.6400146484375,
          "context": "... about the church in Corinth and here in this portion of Scripture. In fact, I'll be preaching from 1 Corinthians 11 this evening as we observe the Lord's Supper. But we find in 1 Corinthians 11, at the end of the pa..."
        },
        {
          "reference": "1 Corinthians 11",
          "sermon_id": "QRS13lJ0CSY",
          "timestamp": 1271.6400146484375,
          "context": "... about the church in Corinth and here in this portion of Scripture. In fact, I'll be preaching from 1 Corinthians 11 this evening as we observe the Lord's Supper. But we find in 1 Corinthians 11, at the end of the pa..."
        }
      ]
    },
    {
      "sermon_id": "bPt92Z2dPIg",
      "sermon_title": "Sermon bPt92Z2dPIg",
      "url": "https://www.youtube.com/watch?v=bPt92Z2dPIg",
      "publish_date": "2025-04-26",
      "occurrences": [
        {
          "reference": "1 Corinthians 6",
          "sermon_id": "bPt92Z2dPIg",
          "timestamp": 1346.780029296875,
          "context": "...rnity to a place called the Lake of Fire. Oh, what grace and what mercy, what love. We find that in 1 Corinthians 6 in verses 19 and 20 that Paul, as he's speaking to the believers there in Corinth, he says what? Kn..."
        },
        {
          "reference": "1 Corinthians 6",
          "sermon_id": "bPt92Z2dPIg",
          "timestamp": 1419.780029296875,
          "context": "what love. We find that in 1 Corinthians 6 in verses 19 and 20 that Paul, as he's speaking to the believers there in Corinth, he says what? Kn..."
        }
      ]
    },
    {
      "sermon_id": "nS3pAoxKMb4",
      "sermon_title": "Sermon nS3pAoxKMb4",
      "url": "https://www.youtube.com/watch?v=nS3pAoxKMb4",
      "publish_date": "2025-04-26",
      "occurrences": [
        {
          "reference": "1 Corinthians 10",
          "sermon_id": "nS3pAoxKMb4",
          "timestamp": 1661.02001953125,
          "context": "... God that You would help us to be aware of and mindful of the promise that You've given us there in 1 Corinthians 10 and verse 13. God that we would actively look for the escape route when that temptation comes, beca..."
        }
      ]
    },
    {
      "sermon_id": "iT8pxOgIv0A",
      "sermon_title": "Sermon iT8pxOgIv0A",
      "url": "https://www.youtube.com/watch?v=iT8pxOgIv0A",
      "publish_date": "2025-04-26",
      "occurrences": [
        {
          "reference": "1 Corinthians 13",
          "sermon_id": "iT8pxOgIv0A",
          "timestamp": 1746.47998046875,
          "context": "... is that we're inciting them to do. Number one, he says that we're to provoke unto love. Unto love. 1 Corinthians 13 deals with the subject matter of charity, and how important that subject matter is. matter is we un..."
        },
        {
          "reference": "1 Corinthians 13",
          "sermon_id": "iT8pxOgIv0A",
          "timestamp": 1809.5799369812012,
          "context": "love. Unto love. 1 Corinthians 13 deals with the subject matter of charity, and how important that subject matter is. matter is we un..."
        }
      ]
    },
    {
      "sermon_id": "YCUS9wAR_oA",
      "sermon_title": "Sermon YCUS9wAR_oA",
      "url": "https://www.youtube.com/watch?v=YCUS9wAR_oA",
      "publish_date": "2025-04-26",
      "occurrences": [
        {
          "reference": "1 Corinthians 6",
          "sermon_id": "YCUS9wAR_oA",
          "timestamp": 2010.1399536132812,
          "context": "... say that? I'm going to do what I want to do. Well, there's a problem if you're a Christian because 1 Corinthians 6, 19 and 20 says, what? Know ye not that your body is the temple of the Holy Ghost which is in you, ..."
        }
      ]
    },
    {
      "sermon_id": "2cDKZaPlI5s",
      "sermon_title": "Sermon 2cDKZaPlI5s",
      "url": "https://www.youtube.com/watch?v=2cDKZaPlI5s",
      "publish_date": "2025-04-26",
      "occurrences": [
        {
          "reference": "1 Corinthians 2",
          "sermon_id": "2cDKZaPlI5s",
          "timestamp": 1403.9199829101562,
          "context": "...re are foolishness unto him, neither can he know them. Why? Because they are spiritually discerned, 1 Corinthians 2. And we find here that God is sent in this indictment against his people"
        },
        {
          "reference": "1 Corinthians 2",
          "sermon_id": "2cDKZaPlI5s",
          "timestamp": 1467.9199829101562,
          "context": "...re are foolishness unto him, neither can he know them. Why? Because they are spiritually discerned, 1 Corinthians 2. And we find here that God is sent in this indictment against his people because they're taking cou..."
        }
      ]
    },
    {
      "sermon_id": "8LNBaTbwuzM",
      "sermon_title": "Sermon 8LNBaTbwuzM",
      "url": "https://www.youtube.com/watch?v=8LNBaTbwuzM",
      "publish_date": "2025-04-26",
      "occurrences": [
        {
          "reference": "1 Corinthians 10",
          "sermon_id": "8LNBaTbwuzM",
          "timestamp": 416.9599914550781,
          "context": "... must understand that we too can sink to some pretty low levels of carnality. The Bible tells us in 1 Corinthians 10, let him that thinketh he standeth, take heed lest he fall. You know, it's absolutely imperative th..."
        }
      ]
    },
    {
      "sermon_id": "dQq2qxx8aHM",
      "sermon_title": "Sermon dQq2qxx8aHM",
      "url": "https://www.youtube.com/watch?v=dQq2qxx8aHM",
      "publish_date": "2025-04-26",
      "occurrences": [
        {
          "reference": "1 Corinthians 9",
          "sermon_id": "dQq2qxx8aHM",
          "timestamp": 299.5400085449219,
          "context": "...ys here as he's writing and challenging these believers in Corinth. Beginning in verse number 23 of 1 Corinthians 9, the Bible says this, and this I do for the gospel's sake, that I might be partaker thereof with yo..."
        }
      ]
    },
    {
      "sermon_id": "nexqP9hAOHU",
      "sermon_title": "Sermon nexqP9hAOHU",
      "url": "https://www.youtube.com/watch?v=nexqP9hAOHU",
      "publish_date": "2025-04-26",
      "occurrences": [
        {
          "reference": "1 Corinthians 16",
          "sermon_id": "nexqP9hAOHU",
          "timestamp": 0.0,
          "context": "...alk with the Lord, and of course, with various things within the church, but Paul mentioned this in 1 Corinthians 16, in verse number 9, he said, For a great door and effectual is opened unto me, and then he ends the..."
        }
      ]
    },
    {
      "sermon_id": "uGo1HL4c1vk",
      "sermon_title": "Sermon uGo1HL4c1vk",
      "url": "https://www.youtube.com/watch?v=uGo1HL4c1vk",
      "publish_date": "2025-04-26",
      "occurrences": [
        {
          "reference": "1 Corinthians 16",
          "sermon_id": "uGo1HL4c1vk",
          "timestamp": 1113.3999633789062,
          "context": "...this charge to Archippus. But understand that Paul understood some things about opposition. Turn to 1 Corinthians 16 if you will. And notice what Paul says here in this portion of Scripture. We'll just look at two ex..."
        },
        {
          "reference": "1 Corinthians 16",
          "sermon_id": "uGo1HL4c1vk",
          "timestamp": 1113.3999633789062,
          "context": "...this charge to Archippus. But understand that Paul understood some things about opposition. Turn to 1 Corinthians 16 if you will. And notice what Paul says here in this portion of Scripture. We'll just look at two ex..."
        },
        {
          "reference": "1 Corinthians 16",
          "sermon_id": "uGo1HL4c1vk",
          "timestamp": 1113.3999633789062,
          "context": "...this charge to Archippus. But understand that Paul understood some things about opposition. Turn to 1 Corinthians 16 if you will. And notice what Paul says here in this portion of Scripture. We'll just look at two ex..."
        }
      ]
    },
    {
      "sermon_id": "d8tHudo0_3I",
      "sermon_title": "Sermon d8tHudo0_3I",
      "url": "https://www.youtube.com/watch?v=d8tHudo0_3I",
      "publish_date": "2025-04-26",
      "occurrences": [
        {
          "reference": "1 Corinthians 9",
          "sermon_id": "d8tHudo0_3I",
          "timestamp": 616.860013961792,
          "context": "...ed. It's a perspective that I need. That we would have this perspective that I am dead here. Notice 1 Corinthians 9 and verse 16. For though I preach the Gospel, I have nothing to glory of, for necessity is laid upo..."
        }
      ]
    }
  ]
}