{
  "book": "Lamentations",
  "sermons": [
    {
      "sermon_id": "iT8pxOgIv0A",
      "sermon_title": "Sermon iT8pxOgIv0A",
      "url": "https://www.youtube.com/watch?v=iT8pxOgIv0A",
      "publish_date": "2025-04-26",
      "occurrences": [
        {
          "reference": "Lamentations 3",
          "sermon_id": "iT8pxOgIv0A",
          "timestamp": 1529.9999694824219,
          "context": "...e has hope, and he speaks about the mercy of God, but he speaks about great is thy faithfulness. In Lamentations 3, in verse number 23. And we find ourselves here looking at this truth that we're to hold fast the p..."
        }
      ]
    }
  ]
}