{
  "chapter": "Deuteronomy 33",
  "sermons": [
    {
      "sermon_id": "09KQDExB3yQ",
      "sermon_title": "Sermon 09KQDExB3yQ",
      "url": "https://www.youtube.com/watch?v=09KQDExB3yQ",
      "publish_date": "2025-04-28",
      "occurrences": [
        {
          "reference": "Deuteronomy 33",
          "sermon_id": "09KQDExB3yQ",
          "timestamp": 1010.1799926757812,
          "context": "...in their census of their population to understand that they're not even mentioned there by Moses in Deuteronomy 33."
        },
        {
          "reference": "Deuteronomy 33",
          "sermon_id": "09KQDExB3yQ",
          "timestamp": 1077.8200073242188,
          "context": "...in their census of their population to understand that they're not even mentioned there by Moses in Deuteronomy 33. Levi, we see that they're both there and again, Levi is just as guilty as Simeon with regard to th..."
        },
        {
          "reference": "Deuteronomy 33",
          "sermon_id": "09KQDExB3yQ",
          "timestamp": 1148.2000122070312,
          "context": "..., the way in which they would be found throughout the land and we'll read in just a moment there in Deuteronomy 33 and verses 10 and 11 and to see what their duties and responsibilities were, but I'd ask this quest..."
        },
        {
          "reference": "Deuteronomy 33",
          "sermon_id": "09KQDExB3yQ",
          "timestamp": 1296.0800170898438,
          "context": "...en, I'd rather be on the Lord's side than the world's side. Amen? And notice what the Bible says in Deuteronomy 33. We'd eventually get here. In Deuteronomy chapter 33, notice what God says through Moses in verses ..."
        },
        {
          "reference": "Deuteronomy 33",
          "sermon_id": "09KQDExB3yQ",
          "timestamp": 1296.0800170898438,
          "context": "...en, I'd rather be on the Lord's side than the world's side. Amen? And notice what the Bible says in Deuteronomy 33. We'd eventually get here. In Deuteronomy chapter 33, notice what God says through Moses in verses ..."
        }
      ]
    },
    {
      "sermon_id": "d7fsLPs8FTY",
      "sermon_title": "Sermon d7fsLPs8FTY",
      "url": "https://www.youtube.com/watch?v=d7fsLPs8FTY",
      "publish_date": "2025-04-28",
      "occurrences": [
        {
          "reference": "Deuteronomy 33",
          "sermon_id": "d7fsLPs8FTY",
          "timestamp": 294.82000732421875,
          "context": "...idon. As we look at these particular statements that are given in verse 13, and we couple that with Deuteronomy 33, remember it's in Deuteronomy 33 that Moses prior to his death, he makes reference to the tribes of..."
        },
        {
          "reference": "Deuteronomy 33",
          "sermon_id": "d7fsLPs8FTY",
          "timestamp": 294.82000732421875,
          "context": "...idon. As we look at these particular statements that are given in verse 13, and we couple that with Deuteronomy 33, remember it's in Deuteronomy 33 that Moses prior to his death, he makes reference to the tribes of..."
        },
        {
          "reference": "Deuteronomy 33",
          "sermon_id": "d7fsLPs8FTY",
          "timestamp": 294.82000732421875,
          "context": "...idon. As we look at these particular statements that are given in verse 13, and we couple that with Deuteronomy 33, remember it's in Deuteronomy 33 that Moses prior to his death, he makes reference to the tribes of..."
        },
        {
          "reference": "Deuteronomy 33",
          "sermon_id": "d7fsLPs8FTY",
          "timestamp": 581.760009765625,
          "context": "...o reluctance on the part of hard work and doing what needed to be done. And we find that it says in Deuteronomy 33, in v. 18, when Moses is sharing the blessings, if you will, before his death, He said to Zebulun, ..."
        },
        {
          "reference": "Deuteronomy 33",
          "sermon_id": "d7fsLPs8FTY",
          "timestamp": 656.2400093078613,
          "context": "done. And we find that it says in Deuteronomy 33, in v. 18, when Moses is sharing the blessings, if you will, before his death, He said to Zebulun, ..."
        },
        {
          "reference": "Deuteronomy 33",
          "sermon_id": "d7fsLPs8FTY",
          "timestamp": 2386.280029296875,
          "context": "...We find that it says that a troop shall overcome him, but he shall overcome at the last. It says in Deuteronomy 33 and verse number 20 that it talks about his enlarging and his strength. And Moses says like a lion ..."
        },
        {
          "reference": "Deuteronomy 33",
          "sermon_id": "d7fsLPs8FTY",
          "timestamp": 2456.880043029785,
          "context": "a troop shall overcome him, but he shall overcome at the last. It says in Deuteronomy 33 and verse number 20 that it talks about his enlarging and his strength. And Moses says like a lion ..."
        }
      ]
    }
  ]
}