{
  "chapter": "Genesis 50",
  "sermons": [
    {
      "sermon_id": "EoTOjgo0SqY",
      "sermon_title": "Sermon EoTOjgo0SqY",
      "url": "https://www.youtube.com/watch?v=EoTOjgo0SqY",
      "publish_date": "2025-04-26",
      "occurrences": [
        {
          "reference": "Genesis 50",
          "sermon_id": "EoTOjgo0SqY",
          "timestamp": 1498.1399841308594,
          "context": "... for evil, but God meant it for good and understanding all of that. And we read all the way through Genesis 50 and many of us are familiar with what happens in Joseph's life, but I would submit to you this even..."
        }
      ]
    }
  ]
}