{
  "chapter": "Romans 6",
  "sermons": [
    {
      "sermon_id": "KVAB3-ajXLM",
      "sermon_title": "Sermon KVAB3-ajXLM",
      "url": "https://www.youtube.com/watch?v=KVAB3-ajXLM",
      "publish_date": "2025-04-26",
      "occurrences": [
        {
          "reference": "Romans 6",
          "sermon_id": "KVAB3-ajXLM",
          "timestamp": 2496.760040283203,
          "context": "...ielded their bodies. It's interesting if you were to go and maybe jot it down in your notes to read Romans 6 about who we yield ourselves to. We are to yield ourselves unto the Lord, and we find that these me..."
        },
        {
          "reference": "Romans 6",
          "sermon_id": "KVAB3-ajXLM",
          "timestamp": 2496.760040283203,
          "context": "...ielded their bodies. It's interesting if you were to go and maybe jot it down in your notes to read Romans 6 about who we yield ourselves to. We are to yield ourselves unto the Lord, and we find that these me..."
        }
      ]
    },
    {
      "sermon_id": "EetmC5JSFHc",
      "sermon_title": "Sermon EetmC5JSFHc",
      "url": "https://www.youtube.com/watch?v=EetmC5JSFHc",
      "publish_date": "2025-04-26",
      "occurrences": [
        {
          "reference": "Romans 6",
          "sermon_id": "EetmC5JSFHc",
          "timestamp": 1078.0400390625,
          "context": "... are one. I'm thankful that He's given us this promise here. We understand that, as we mentioned in Romans 6, that the gift of God is eternal life through Jesus Christ our Lord. Here He says My sheep, they he..."
        },
        {
          "reference": "Romans 6",
          "sermon_id": "EetmC5JSFHc",
          "timestamp": 1149.1000366210938,
          "context": "... tells us this, that sin no longer has dominion over us. That caused me to rejoice greatly. Turn to Romans 6, if you will, and you think about this truth of being saved, being a child of God. Understand that ..."
        },
        {
          "reference": "Romans 6",
          "sermon_id": "EetmC5JSFHc",
          "timestamp": 1149.1000366210938,
          "context": "... tells us this, that sin no longer has dominion over us. That caused me to rejoice greatly. Turn to Romans 6, if you will, and you think about this truth of being saved, being a child of God. Understand that ..."
        },
        {
          "reference": "Romans 6",
          "sermon_id": "EetmC5JSFHc",
          "timestamp": 1287.7000350952148,
          "context": "...fact that He is victorious. I'm thankful that His victory enables me to have victory. We're here in Romans 6. Look over in Romans 7, if you will, and look at verses 24 and 25. Paul cries out almost in despair..."
        }
      ]
    },
    {
      "sermon_id": "nS3pAoxKMb4",
      "sermon_title": "Sermon nS3pAoxKMb4",
      "url": "https://www.youtube.com/watch?v=nS3pAoxKMb4",
      "publish_date": "2025-04-26",
      "occurrences": [
        {
          "reference": "Romans 6",
          "sermon_id": "nS3pAoxKMb4",
          "timestamp": 865.9400024414062,
          "context": "...to help them understand this truth of being delivered from the very power of sin. The Bible says in Romans 6, and we'll pick it up in verse 12. Romans 6 and verse 12, the Bible says, Romans 6 12, let not sin ..."
        },
        {
          "reference": "Romans 6",
          "sermon_id": "nS3pAoxKMb4",
          "timestamp": 865.9400024414062,
          "context": "...to help them understand this truth of being delivered from the very power of sin. The Bible says in Romans 6, and we'll pick it up in verse 12. Romans 6 and verse 12, the Bible says, Romans 6 12, let not sin ..."
        },
        {
          "reference": "Romans 6",
          "sermon_id": "nS3pAoxKMb4",
          "timestamp": 865.9400024414062,
          "context": "...to help them understand this truth of being delivered from the very power of sin. The Bible says in Romans 6, and we'll pick it up in verse 12. Romans 6 and verse 12, the Bible says, Romans 6 12, let not sin ..."
        },
        {
          "reference": "Romans 6",
          "sermon_id": "nS3pAoxKMb4",
          "timestamp": 938.0,
          "context": "the Bible says, Romans 6 12, let not sin therefore reign in your mortal body, that you should obey it in the lust thereof, n..."
        }
      ]
    },
    {
      "sermon_id": "WhaPo-g3nqA",
      "sermon_title": "Sermon WhaPo-g3nqA",
      "url": "https://www.youtube.com/watch?v=WhaPo-g3nqA",
      "publish_date": "2025-04-26",
      "occurrences": [
        {
          "reference": "Romans 6",
          "sermon_id": "WhaPo-g3nqA",
          "timestamp": 2078.179962158203,
          "context": "... in us. It's not me trying, it's me yielding. Right? And as I yield my members, as he says there in Romans 6, 7, and 8, and you read those passages of Scripture and you see how Paul is really giving a great d..."
        }
      ]
    }
  ]
}